<annotation verified="no">
  <folder>han_lei</folder>
  <filename>IMG_20211022_151444</filename>
  <path>C:\Users\jasul\Desktop\shapes\han_lei\IMG_20211022_151444.jpg</path>
  <source>
    <database>Unknown</database>
  </source>
  <size>
    <width>4000</width>
    <height>3000</height>
    <depth>3</depth>
  </size>
  <segmented>0</segmented>
  <object>
    <type>bndbox</type>
    <name>3</name>
    <pose>Unspecified</pose>
    <truncated>0</truncated>
    <difficult>0</difficult>
    <bndbox>
      <xmin>469</xmin>
      <ymin>114</ymin>
      <xmax>647</xmax>
      <ymax>229</ymax>
    </bndbox>
  </object>
  <object>
    <type>bndbox</type>
    <name>4</name>
    <pose>Unspecified</pose>
    <truncated>0</truncated>
    <difficult>0</difficult>
    <bndbox>
      <xmin>1950</xmin>
      <ymin>1385</ymin>
      <xmax>2191</xmax>
      <ymax>1595</ymax>
    </bndbox>
  </object>
  <object>
    <type>robndbox</type>
    <name>3</name>
    <pose>Unspecified</pose>
    <truncated>0</truncated>
    <difficult>0</difficult>
    <robndbox>
      <cx>558.0934</cx>
      <cy>164.0796</cy>
      <w>176.157</w>
      <h>114.8281</h>
      <angle>0.1</angle>
    </robndbox>
  </object>
  <object>
    <type>robndbox</type>
    <name>4</name>
    <pose>Unspecified</pose>
    <truncated>0</truncated>
    <difficult>0</difficult>
    <robndbox>
      <cx>2071.5</cx>
      <cy>1489.0</cy>
      <w>221.9219</w>
      <h>187.7543</h>
      <angle>2.981593</angle>
    </robndbox>
  </object>
</annotation>
